yaqd_dwyer/VERSION
yaqd_dwyer/__init__.py
yaqd_dwyer/__version__.py
yaqd_dwyer/_dwyer_16b.py
yaqd_dwyer/_dwyer_16c.py
yaqd_dwyer/dwyer-16b.avpr
yaqd_dwyer/dwyer-16b.toml
yaqd_dwyer/dwyer-16c.avpr
yaqd_dwyer/dwyer-16c.toml
yaqd_dwyer-2023.5.0.dist-info/entry_points.txt
yaqd_dwyer-2023.5.0.dist-info/LICENSE
yaqd_dwyer-2023.5.0.dist-info/WHEEL
yaqd_dwyer-2023.5.0.dist-info/METADATA
yaqd_dwyer-2023.5.0.dist-info/RECORD
