Metadata-Version: 2.1
Name: yaqd-dwyer
Version: 2023.5.0
Summary: yaq daemons for Dwyer instruments & controllers
Home-page: https://yaq.fyi
Author: yaq developers
Requires-Python: >=3.7
Classifier: Development Status :: 2 - Pre-Alpha
Classifier: Intended Audience :: Science/Research
Classifier: License :: OSI Approved :: GNU Lesser General Public License v3 (LGPLv3)
Classifier: Natural Language :: English
Classifier: Programming Language :: Python :: 3
Classifier: Programming Language :: Python :: 3.7
Classifier: Programming Language :: Python :: 3.8
Classifier: Topic :: Scientific/Engineering
Requires-Dist: minimalmodbus
Requires-Dist: pyserial
Requires-Dist: yaqd-core>=2020.06.3
Requires-Dist: black ; extra == "dev"
Requires-Dist: pre-commit ; extra == "dev"
Project-URL: Issues, https://gitlab.com/yaq/yaqd-dwyer/issues
Project-URL: Source, https://gitlab.com/yaq/yaqd-dwyer
Provides-Extra: dev
